easyprophet/__init__.py
easyprophet/easyprophet.py
easyprophet/hello_world.py
easyprophet-1.1.2.dist-info/AUTHORS.md
easyprophet-1.1.2.dist-info/LICENSE
easyprophet-1.1.2.dist-info/METADATA
easyprophet-1.1.2.dist-info/WHEEL
easyprophet-1.1.2.dist-info/top_level.txt
easyprophet-1.1.2.dist-info/RECORD
