Metadata-Version: 2.1
Name: easyprophet
Version: 1.1.2
Summary: Python package developed to simplify Prophet application to any data.
Home-page: https://github.com/federicodecillia/easyprophet
Author: Federico De Cillia
License: UNKNOWN
Platform: UNKNOWN
Classifier: Programming Language :: Python :: 3
Classifier: License :: OSI Approved :: MIT License
Classifier: Operating System :: Microsoft :: Windows
Requires-Python: >=3.6
License-File: LICENSE
License-File: AUTHORS.md
Requires-Dist: numpy
Requires-Dist: pandas
Requires-Dist: plotly
Requires-Dist: scikit-learn
Requires-Dist: scipy
